django_enforced_choices/__init__.py
django_enforced_choices/models.py
django_enforced_choices/fields/__init__.py
django_enforced_choices/fields/postgres.py
django_enforced_choices-0.2.0.dist-info/LICENSE
django_enforced_choices-0.2.0.dist-info/METADATA
django_enforced_choices-0.2.0.dist-info/WHEEL
django_enforced_choices-0.2.0.dist-info/top_level.txt
django_enforced_choices-0.2.0.dist-info/RECORD
